MANIFEST.in
README.rst
setup.py
grvlms_proctoring/__about__.py
grvlms_proctoring/__init__.py
grvlms_proctoring/plugin.py
grvlms_proctoring.egg-info/PKG-INFO
grvlms_proctoring.egg-info/SOURCES.txt
grvlms_proctoring.egg-info/dependency_links.txt
grvlms_proctoring.egg-info/entry_points.txt
grvlms_proctoring.egg-info/requires.txt
grvlms_proctoring.egg-info/top_level.txt
grvlms_proctoring/patches/.gitignore
grvlms_proctoring/patches/cms-env
grvlms_proctoring/patches/lms-env
grvlms_proctoring/patches/openedx-auth
grvlms_proctoring/patches/openedx-dockerfile-pre-assets
grvlms_proctoring/templates/proctoring/apps/.gitignore
grvlms_proctoring/templates/proctoring/build/.gitignore
grvlms_proctoring/templates/proctoring/hooks/.gitignore